{"split0_index": [10, 11, 12, 13, 14, 15, 16, 17, 18, 19], "split0_pred": [1, 1, 1, 1, 1, 1, 0, 0, 1, 1], "split0_test": [0, 0, 0, 0, 0, 0, 0, 0, 0, 1], "split0_notXOR": [0, 0, 0, 0, 0, 0, 1, 1, 0, 1], "split0_prob": [1.0, 1.0, 1.0, 1.0, 1.0, 1.0, 0.0, 0.0, 1.0, 1.0], "split1_index": [20, 21, 22, 23, 24, 25, 26, 27, 28, 29], "split1_pred": [0, 0, 0, 1, 0, 0, 0, 0, 0, 1], "split1_test": [0, 1, 0, 0, 0, 0, 0, 0, 0, 1], "split1_notXOR": [1, 0, 1, 0, 1, 1, 1, 1, 1, 1], "split1_prob": [0.0, 0.0, 0.0, 1.0, 0.0, 0.0, 0.0, 0.0, 0.0, 1.0], "split2_index": [30, 31, 32, 33, 34, 35, 36, 37, 38, 39], "split2_pred": [0, 1, 0, 0, 0, 0, 0, 0, 0, 1], "split2_test": [0, 0, 0, 0, 0, 0, 0, 0, 0, 1], "split2_notXOR": [1, 0, 1, 1, 1, 1, 1, 1, 1, 1], "split2_prob": [0.0, 0.9999929663208824, 0.0, 0.0, 0.0, 0.0, 0.0, 0.0, 0.0, 0.9999999303514098], "split3_index": [40, 41, 42, 43, 44, 45, 46, 47, 48, 49], "split3_pred": [0, 1, 0, 0, 0, 0, 0, 0, 0, 1], "split3_test": [0, 0, 0, 0, 0, 0, 0, 0, 0, 1], "split3_notXOR": [1, 0, 1, 1, 1, 1, 1, 1, 1, 1], "split3_prob": [0.0, 0.9999952472585731, 0.0, 0.0, 0.0, 0.0, 0.0, 0.0, 0.0, 0.9999999059406486], "split4_index": [50, 51, 52, 53, 54, 55, 56, 57, 58, 59], "split4_pred": [0, 1, 0, 0, 0, 0, 0, 0, 0, 0], "split4_test": [0, 0, 0, 0, 0, 0, 0, 0, 0, 1], "split4_notXOR": [1, 0, 1, 1, 1, 1, 1, 1, 1, 0], "split4_prob": [0.0, 0.9999941991354871, 0.0, 0.0, 0.0, 0.0, 0.0, 0.0, 0.0, 0.04689421467281537], "split5_index": [60, 61, 62, 63, 64, 65, 66, 67, 68, 69], "split5_pred": [0, 1, 0, 0, 0, 0, 0, 0, 0, 1], "split5_test": [0, 0, 0, 0, 0, 0, 0, 0, 0, 1], "split5_notXOR": [1, 0, 1, 1, 1, 1, 1, 1, 1, 1], "split5_prob": [0.0, 0.9999789250210739, 0.0, 0.0, 0.0, 0.0, 0.0, 0.0, 0.0, 0.9999141680552135]}